lykkellemainNAmerica/__init__.py
lykkellemainNAmerica/healthcheck5.py
lykkellemainNAmerica/maincalculationprogeod5.py
lykkellemainNAmerica/mainmasterprogeod5.py
lykkellemainNAmerica-0.1.2.dist-info/LICENSE
lykkellemainNAmerica-0.1.2.dist-info/METADATA
lykkellemainNAmerica-0.1.2.dist-info/WHEEL
lykkellemainNAmerica-0.1.2.dist-info/top_level.txt
lykkellemainNAmerica-0.1.2.dist-info/RECORD
